{
    "id": 4,
    "name": "flying",
    "names": [
        {
            "language": {
                "name": "ja-Hrkt",
                "id": 1
            },
            "name": "ひこう"
        },
        {
            "language": {
                "name": "ko",
                "id": 3
            },
            "name": "비행"
        },
        {
            "language": {
                "name": "fr",
                "id": 5
            },
            "name": "Aérien"
        },
        {
            "language": {
                "name": "de",
                "id": 6
            },
            "name": "Flug"
        },
        {
            "language": {
                "name": "es",
                "id": 7
            },
            "name": "Volador"
        },
        {
            "language": {
                "name": "it",
                "id": 8
            },
            "name": "Volante"
        },
        {
            "language": {
                "name": "en",
                "id": 9
            },
            "name": "Flying"
        }
    ],
    "pokemon_species": [
        {
            "name": "pidgey",
            "id": 16
        },
        {
            "name": "pidgeotto",
            "id": 17
        },
        {
            "name": "pidgeot",
            "id": 18
        },
        {
            "name": "spearow",
            "id": 21
        },
        {
            "name": "fearow",
            "id": 22
        },
        {
            "name": "zubat",
            "id": 41
        },
        {
            "name": "golbat",
            "id": 42
        },
        {
            "name": "farfetchd",
            "id": 83
        },
        {
            "name": "doduo",
            "id": 84
        },
        {
            "name": "dodrio",
            "id": 85
        },
        {
            "name": "aerodactyl",
            "id": 142
        },
        {
            "name": "hoothoot",
            "id": 163
        },
        {
            "name": "noctowl",
            "id": 164
        },
        {
            "name": "crobat",
            "id": 169
        },
        {
            "name": "togetic",
            "id": 176
        },
        {
            "name": "natu",
            "id": 177
        },
        {
            "name": "xatu",
            "id": 178
        },
        {
            "name": "murkrow",
            "id": 198
        },
        {
            "name": "skarmory",
            "id": 227
        },
        {
            "name": "taillow",
            "id": 276
        },
        {
            "name": "swellow",
            "id": 277
        },
        {
            "name": "wingull",
            "id": 278
        },
        {
            "name": "pelipper",
            "id": 279
        },
        {
            "name": "swablu",
            "id": 333
        },
        {
            "name": "altaria",
            "id": 334
        },
        {
            "name": "starly",
            "id": 396
        },
        {
            "name": "staravia",
            "id": 397
        },
        {
            "name": "staraptor",
            "id": 398
        },
        {
            "name": "honchkrow",
            "id": 430
        },
        {
            "name": "chatot",
            "id": 441
        },
        {
            "name": "togekiss",
            "id": 468
        },
        {
            "name": "pidove",
            "id": 519
        },
        {
            "name": "tranquill",
            "id": 520
        },
        {
            "name": "unfezant",
            "id": 521
        },
        {
            "name": "woobat",
            "id": 527
        },
        {
            "name": "swoobat",
            "id": 528
        },
        {
            "name": "sigilyph",
            "id": 561
        },
        {
            "name": "archen",
            "id": 566
        },
        {
            "name": "archeops",
            "id": 567
        },
        {
            "name": "ducklett",
            "id": 580
        },
        {
            "name": "swanna",
            "id": 581
        },
        {
            "name": "rufflet",
            "id": 627
        },
        {
            "name": "braviary",
            "id": 628
        },
        {
            "name": "vullaby",
            "id": 629
        },
        {
            "name": "mandibuzz",
            "id": 630
        },
        {
            "name": "fletchling",
            "id": 661
        },
        {
            "name": "fletchinder",
            "id": 662
        },
        {
            "name": "talonflame",
            "id": 663
        },
        {
            "name": "noibat",
            "id": 714
        },
        {
            "name": "noivern",
            "id": 715
        },
        {
            "name": "rowlet",
            "id": 722
        },
        {
            "name": "dartrix",
            "id": 723
        },
        {
            "name": "decidueye",
            "id": 724
        },
        {
            "name": "pikipek",
            "id": 731
        },
        {
            "name": "trumbeak",
            "id": 732
        },
        {
            "name": "toucannon",
            "id": 733
        },
        {
            "name": "oricorio",
            "id": 741
        }
    ]
}